odoo/addons/pos_margin/README.rst
odoo/addons/pos_margin/__init__.py
odoo/addons/pos_margin/__manifest__.py
odoo/addons/pos_margin/i18n/es.po
odoo/addons/pos_margin/i18n/fr.po
odoo/addons/pos_margin/i18n/it.po
odoo/addons/pos_margin/i18n/nl_NL.po
odoo/addons/pos_margin/i18n/pos_margin.pot
odoo/addons/pos_margin/migrations/12.0.2.0.0/pre-migration.py
odoo/addons/pos_margin/models/__init__.py
odoo/addons/pos_margin/models/pos_config.py
odoo/addons/pos_margin/models/pos_order.py
odoo/addons/pos_margin/models/pos_order_line.py
odoo/addons/pos_margin/readme/CONFIGURE.rst
odoo/addons/pos_margin/readme/CONTRIBUTORS.rst
odoo/addons/pos_margin/readme/DESCRIPTION.rst
odoo/addons/pos_margin/readme/HISTORY.rst
odoo/addons/pos_margin/readme/ROADMAP.rst
odoo/addons/pos_margin/readme/USAGE.rst
odoo/addons/pos_margin/report/__init__.py
odoo/addons/pos_margin/report/pos_order_report.py
odoo/addons/pos_margin/static/description/icon.png
odoo/addons/pos_margin/static/description/index.html
odoo/addons/pos_margin/static/description/pos_config_form.png
odoo/addons/pos_margin/static/description/pos_front_end.png
odoo/addons/pos_margin/static/description/pos_order_form.png
odoo/addons/pos_margin/static/src/css/pos_margin.css
odoo/addons/pos_margin/static/src/js/OrderSummaryMargin.js
odoo/addons/pos_margin/static/src/js/OrderWidget.js
odoo/addons/pos_margin/static/src/js/models.js
odoo/addons/pos_margin/static/src/xml/pos_margin.xml
odoo/addons/pos_margin/tests/__init__.py
odoo/addons/pos_margin/tests/test_module.py
odoo/addons/pos_margin/views/templates.xml
odoo/addons/pos_margin/views/view_pos_config.xml
odoo/addons/pos_margin/views/view_pos_order.xml
odoo14_addon_pos_margin-14.0.1.0.4.dist-info/METADATA
odoo14_addon_pos_margin-14.0.1.0.4.dist-info/WHEEL
odoo14_addon_pos_margin-14.0.1.0.4.dist-info/top_level.txt
odoo14_addon_pos_margin-14.0.1.0.4.dist-info/RECORD
